google_analytics/__init__.py
google_analytics/admin.py
google_analytics/models.py
google_analytics/migrations/0001_initial.py
google_analytics/migrations/__init__.py
google_analytics/templates/google_analytics/analytics_async_template.html
google_analytics/templates/google_analytics/analytics_template.html
google_analytics/templatetags/__init__.py
google_analytics/templatetags/analytics.py
django_ga-0.2.2.dist-info/METADATA
django_ga-0.2.2.dist-info/WHEEL
django_ga-0.2.2.dist-info/top_level.txt
django_ga-0.2.2.dist-info/RECORD
